joris2k_ble/__init__.py
joris2k_ble/connection.py
joris2k_ble/joris2kblecli.py
joris2k_ble/smartmeter.py
python_joris2k_ble-0.1.0.dist-info/LICENSE
python_joris2k_ble-0.1.0.dist-info/METADATA
python_joris2k_ble-0.1.0.dist-info/WHEEL
python_joris2k_ble-0.1.0.dist-info/entry_points.txt
python_joris2k_ble-0.1.0.dist-info/top_level.txt
python_joris2k_ble-0.1.0.dist-info/RECORD
