Metadata-Version: 2.1
Name: python-joris2k-ble
Version: 0.1.0
Summary: Joris2k bluetooth low energy (BLE) devices library
Home-page: https://gitlab.com/jorisdobbelsteen/python-joris2k-ble/
Author: Joris Dobbelsteen
Author-email: joris@familiedobbelsteen.nl
Maintainer: Joris Dobbelsteen
Maintainer-email: joris@familiedobbelsteen.nl
License: MIT
Platform: UNKNOWN
Requires-Python: >=3.6
License-File: LICENSE
Requires-Dist: bluepy (>=1.0.5)
Requires-Dist: click
Requires-Dist: construct
Requires-Dist: click-datetime
